<?xml version="1.0"?>
<FanControlConfigV2 xmlns:xsd="http://www.w3.org/2001/XMLSchema" xmlns:xsi="http://www.w3.org/2001/XMLSchema-instance">
  <NotebookModel>Acer Predator G3-572</NotebookModel>
  <Author>Chandradeep Dey</Author>
  <EcPollInterval>3000</EcPollInterval>
  <ReadWriteWords>true</ReadWriteWords>
  <CriticalTemperature>90</CriticalTemperature>
  <FanConfigurations>
    <FanConfiguration>
      <ReadRegister>19</ReadRegister>
      <WriteRegister>55</WriteRegister>
      <MinSpeedValue>0</MinSpeedValue>
      <MaxSpeedValue>100</MaxSpeedValue>
      <IndependentReadMinMaxValues>true</IndependentReadMinMaxValues>
      <MinSpeedValueRead>0</MinSpeedValueRead>
      <MaxSpeedValueRead>6122</MaxSpeedValueRead>
      <ResetRequired>true</ResetRequired>
      <FanSpeedResetValue>50</FanSpeedResetValue>
      <FanDisplayName>CPU fan</FanDisplayName>
      <TemperatureThresholds>
        <TemperatureThreshold>
          <UpThreshold>0</UpThreshold>
          <DownThreshold>0</DownThreshold>
          <FanSpeed>0</FanSpeed>
        </TemperatureThreshold>
        <TemperatureThreshold>
          <UpThreshold>40</UpThreshold>
          <DownThreshold>40</DownThreshold>
          <FanSpeed>30</FanSpeed>
        </TemperatureThreshold>
        <TemperatureThreshold>
          <UpThreshold>42</UpThreshold>
          <DownThreshold>41</DownThreshold>
          <FanSpeed>32</FanSpeed>
        </TemperatureThreshold>
        <TemperatureThreshold>
          <UpThreshold>44</UpThreshold>
          <DownThreshold>43</DownThreshold>
          <FanSpeed>34</FanSpeed>
        </TemperatureThreshold>
        <TemperatureThreshold>
          <UpThreshold>48</UpThreshold>
          <DownThreshold>46</DownThreshold>
          <FanSpeed>36</FanSpeed>
        </TemperatureThreshold>
        <TemperatureThreshold>
          <UpThreshold>52</UpThreshold>
          <DownThreshold>50</DownThreshold>
          <FanSpeed>38</FanSpeed>
        </TemperatureThreshold>
        <TemperatureThreshold>
          <UpThreshold>54</UpThreshold>
          <DownThreshold>53</DownThreshold>
          <FanSpeed>41</FanSpeed>
        </TemperatureThreshold>
        <TemperatureThreshold>
          <UpThreshold>58</UpThreshold>
          <DownThreshold>56</DownThreshold>
          <FanSpeed>44</FanSpeed>
        </TemperatureThreshold>
        <TemperatureThreshold>
          <UpThreshold>62</UpThreshold>
          <DownThreshold>60</DownThreshold>
          <FanSpeed>47</FanSpeed>
        </TemperatureThreshold>
        <TemperatureThreshold>
          <UpThreshold>64</UpThreshold>
          <DownThreshold>63</DownThreshold>
          <FanSpeed>50</FanSpeed>
        </TemperatureThreshold>
        <TemperatureThreshold>
          <UpThreshold>68</UpThreshold>
          <DownThreshold>66</DownThreshold>
          <FanSpeed>55</FanSpeed>
        </TemperatureThreshold>
        <TemperatureThreshold>
          <UpThreshold>72</UpThreshold>
          <DownThreshold>70</DownThreshold>
          <FanSpeed>61</FanSpeed>
        </TemperatureThreshold>
        <TemperatureThreshold>
          <UpThreshold>74</UpThreshold>
          <DownThreshold>73</DownThreshold>
          <FanSpeed>68</FanSpeed>
        </TemperatureThreshold>
        <TemperatureThreshold>
          <UpThreshold>78</UpThreshold>
          <DownThreshold>76</DownThreshold>
          <FanSpeed>76</FanSpeed>
        </TemperatureThreshold>
        <TemperatureThreshold>
          <UpThreshold>82</UpThreshold>
          <DownThreshold>80</DownThreshold>
          <FanSpeed>85</FanSpeed>
        </TemperatureThreshold>
        <TemperatureThreshold>
          <UpThreshold>84</UpThreshold>
          <DownThreshold>83</DownThreshold>
          <FanSpeed>94</FanSpeed>
        </TemperatureThreshold>
        <TemperatureThreshold>
          <UpThreshold>88</UpThreshold>
          <DownThreshold>86</DownThreshold>
          <FanSpeed>100</FanSpeed>
        </TemperatureThreshold>
      </TemperatureThresholds>
      <FanSpeedPercentageOverrides />
    </FanConfiguration>
    <FanConfiguration>
      <ReadRegister>21</ReadRegister>
      <WriteRegister>58</WriteRegister>
      <MinSpeedValue>0</MinSpeedValue>
      <MaxSpeedValue>100</MaxSpeedValue>
      <IndependentReadMinMaxValues>true</IndependentReadMinMaxValues>
      <MinSpeedValueRead>0</MinSpeedValueRead>
      <MaxSpeedValueRead>6122</MaxSpeedValueRead>
      <ResetRequired>true</ResetRequired>
      <FanSpeedResetValue>50</FanSpeedResetValue>
      <FanDisplayName>GPU fan</FanDisplayName>
      <TemperatureThresholds>
        <TemperatureThreshold>
          <UpThreshold>0</UpThreshold>
          <DownThreshold>0</DownThreshold>
          <FanSpeed>0</FanSpeed>
        </TemperatureThreshold>
        <TemperatureThreshold>
          <UpThreshold>40</UpThreshold>
          <DownThreshold>40</DownThreshold>
          <FanSpeed>22</FanSpeed>
        </TemperatureThreshold>
        <TemperatureThreshold>
          <UpThreshold>42</UpThreshold>
          <DownThreshold>41</DownThreshold>
          <FanSpeed>24</FanSpeed>
        </TemperatureThreshold>
        <TemperatureThreshold>
          <UpThreshold>44</UpThreshold>
          <DownThreshold>43</DownThreshold>
          <FanSpeed>26</FanSpeed>
        </TemperatureThreshold>
        <TemperatureThreshold>
          <UpThreshold>48</UpThreshold>
          <DownThreshold>46</DownThreshold>
          <FanSpeed>28</FanSpeed>
        </TemperatureThreshold>
        <TemperatureThreshold>
          <UpThreshold>52</UpThreshold>
          <DownThreshold>50</DownThreshold>
          <FanSpeed>30</FanSpeed>
        </TemperatureThreshold>
        <TemperatureThreshold>
          <UpThreshold>54</UpThreshold>
          <DownThreshold>53</DownThreshold>
          <FanSpeed>34</FanSpeed>
        </TemperatureThreshold>
        <TemperatureThreshold>
          <UpThreshold>58</UpThreshold>
          <DownThreshold>56</DownThreshold>
          <FanSpeed>38</FanSpeed>
        </TemperatureThreshold>
        <TemperatureThreshold>
          <UpThreshold>62</UpThreshold>
          <DownThreshold>60</DownThreshold>
          <FanSpeed>42</FanSpeed>
        </TemperatureThreshold>
        <TemperatureThreshold>
          <UpThreshold>64</UpThreshold>
          <DownThreshold>63</DownThreshold>
          <FanSpeed>46</FanSpeed>
        </TemperatureThreshold>
        <TemperatureThreshold>
          <UpThreshold>68</UpThreshold>
          <DownThreshold>66</DownThreshold>
          <FanSpeed>52</FanSpeed>
        </TemperatureThreshold>
        <TemperatureThreshold>
          <UpThreshold>72</UpThreshold>
          <DownThreshold>70</DownThreshold>
          <FanSpeed>59</FanSpeed>
        </TemperatureThreshold>
        <TemperatureThreshold>
          <UpThreshold>74</UpThreshold>
          <DownThreshold>73</DownThreshold>
          <FanSpeed>67</FanSpeed>
        </TemperatureThreshold>
        <TemperatureThreshold>
          <UpThreshold>78</UpThreshold>
          <DownThreshold>76</DownThreshold>
          <FanSpeed>76</FanSpeed>
        </TemperatureThreshold>
        <TemperatureThreshold>
          <UpThreshold>82</UpThreshold>
          <DownThreshold>80</DownThreshold>
          <FanSpeed>86</FanSpeed>
        </TemperatureThreshold>
        <TemperatureThreshold>
          <UpThreshold>84</UpThreshold>
          <DownThreshold>83</DownThreshold>
          <FanSpeed>96</FanSpeed>
        </TemperatureThreshold>
        <TemperatureThreshold>
          <UpThreshold>88</UpThreshold>
          <DownThreshold>86</DownThreshold>
          <FanSpeed>100</FanSpeed>
        </TemperatureThreshold>
      </TemperatureThresholds>
      <FanSpeedPercentageOverrides />
    </FanConfiguration>
  </FanConfigurations>
  <RegisterWriteConfigurations>
    <RegisterWriteConfiguration>
      <WriteMode>Set</WriteMode>
      <WriteOccasion>OnInitialization</WriteOccasion>
      <Register>34</Register>
      <Value>12</Value>
      <ResetRequired>true</ResetRequired>
      <ResetValue>4</ResetValue>
      <ResetWriteMode>Set</ResetWriteMode>
      <Description>CPU fan manual mode</Description>
    </RegisterWriteConfiguration>
    <RegisterWriteConfiguration>
      <WriteMode>Set</WriteMode>
      <WriteOccasion>OnInitialization</WriteOccasion>
      <Register>33</Register>
      <Value>48</Value>
      <ResetRequired>true</ResetRequired>
      <ResetValue>16</ResetValue>
      <ResetWriteMode>Set</ResetWriteMode>
      <Description>GPU fan manual mode</Description>
    </RegisterWriteConfiguration>
    <RegisterWriteConfiguration>
      <WriteMode>Set</WriteMode>
      <WriteOccasion>OnInitialization</WriteOccasion>
      <Register>16</Register>
      <Value>0</Value>
      <ResetRequired>true</ResetRequired>
      <ResetValue>1</ResetValue>
      <ResetWriteMode>Set</ResetWriteMode>
      <Description>CoolBoost off</Description>
    </RegisterWriteConfiguration>
  </RegisterWriteConfigurations>
</FanControlConfigV2>
